{
  "type": "FeatureCollection",
  "features": [
    {
      "type": "Feature",
      "properties": {
        "stroke": "#db1414",
        "stroke-width": 2,
        "stroke-opacity": 1,
        "fill": "#ee1111",
        "fill-opacity": 0.5
      },
      "geometry": {
        "coordinates": [
          [
            [
              114.44130675021006,
              42.084914350742594
            ],
            [
              112.94570418790249,
              41.5335998146125
            ],
            [
              112.7280995282897,
              40.84346319005354
            ],
            [
              112.77544750418491,
              39.32845107326273
            ],
            [
              113.62832083582316,
              37.167224699435394
            ],
            [
              120.1078133237304,
              40.32520159451198
            ],
            [
              114.44130675021006,
              42.084914350742594
            ]
          ]
        ],
        "type": "Polygon"
      },
      "id": 0
    }
  ]
}
